starlette_apispec/__init__.py
starlette_apispec/schemas.py
starlette_apispec-2.2.1.dist-info/LICENSE
starlette_apispec-2.2.1.dist-info/METADATA
starlette_apispec-2.2.1.dist-info/WHEEL
starlette_apispec-2.2.1.dist-info/RECORD
