Metadata-Version: 2.1
Name: starlette-apispec
Version: 2.2.1
Summary: APISpec support for starlette
Home-page: https://github.com/Woile/starlette-apispec
License: BSD-3-Clause
Keywords: openapi,api,swagger
Author: Santiago Fraire Willemoes
Author-email: santiwilly@gmail.com
Requires-Python: >=3.8,<4.0
Classifier: Environment :: Web Environment
Classifier: Intended Audience :: Developers
Classifier: License :: OSI Approved :: BSD License
Classifier: Operating System :: OS Independent
Classifier: Programming Language :: Python :: 3
Classifier: Programming Language :: Python :: 3.8
Classifier: Programming Language :: Python :: 3.9
Classifier: Programming Language :: Python :: 3.10
Classifier: Programming Language :: Python :: 3.11
Classifier: Programming Language :: Python :: 3.12
Classifier: Programming Language :: Python :: 3.6
Classifier: Programming Language :: Python :: 3.7
Classifier: Topic :: Internet :: WWW/HTTP
Requires-Dist: apispec (>=1,<7)
Requires-Dist: pyyaml (>=5.1,<7.0)
Requires-Dist: starlette (>=0.11)
